pyawsopstoolkit_insights/__init__.py
pyawsopstoolkit_insights/__validations__.py
pyawsopstoolkit_insights/iam.py
pyawsopstoolkit_insights-0.1.0.dist-info/LICENSE
pyawsopstoolkit_insights-0.1.0.dist-info/METADATA
pyawsopstoolkit_insights-0.1.0.dist-info/WHEEL
pyawsopstoolkit_insights-0.1.0.dist-info/top_level.txt
pyawsopstoolkit_insights-0.1.0.dist-info/RECORD
